[{
    "ID": "I01",
    "Valor": 0,
    "Quantidade": 0,
    "Margem": 0
}, {
    "ID": "I02",
    "Valor": 0,
    "Quantidade": 0,
    "Margem": 0
}, {
    "ID": "I03",
    "Valor": 0,
    "Quantidade": 0,
    "Margem": 0
}, {
    "ID": "I04",
    "Valor": 0,
    "Quantidade": 0,
    "Margem": 0
}, {
    "ID": "I05",
    "Valor": 0,
    "Quantidade": 0,
    "Margem": 0
}, {
    "ID": "I06",
    "Valor": 0,
    "Quantidade": 0,
    "Margem": 0
}, {
    "ID": "I07",
    "Valor": 0,
    "Quantidade": 0,
    "Margem": 0
}, {
    "ID": "I08",
    "Valor": 0,
    "Quantidade": 0,
    "Margem": 0
}, {
    "ID": "I09",
    "Valor": 0,
    "Quantidade": 0,
    "Margem": 0
}, {
    "ID": "I10",
    "Valor": 0,
    "Quantidade": 0,
    "Margem": 0
}, {
    "ID": "I11",
    "Valor": 0,
    "Quantidade": 0,
    "Margem": 0
}, {
    "ID": "I12",
    "Valor": 0,
    "Quantidade": 0,
    "Margem": 0
}, {
    "ID": "I13",
    "Valor": 0,
    "Quantidade": 0,
    "Margem": 0
}, {
    "ID": "I14",
    "Valor": 0,
    "Quantidade": 0,
    "Margem": 0
}, {
    "ID": "I15",
    "Valor": 0,
    "Quantidade": 0,
    "Margem": 0
}, {
    "ID": "I16",
    "Valor": 0,
    "Quantidade": 0,
    "Margem": 0
}, {
    "ID": "I17",
    "Valor": 0,
    "Quantidade": 0,
    "Margem": 0
}, {
    "ID": "I18",
    "Valor": 0,
    "Quantidade": 0,
    "Margem": 0
}, {
    "ID": "I19",
    "Valor": 0,
    "Quantidade": 0,
    "Margem": 0
}, {
    "ID": "I20",
    "Valor": 0,
    "Quantidade": 0,
    "Margem": 0
}, {
    "ID": "I21",
    "Valor": 0,
    "Quantidade": 0,
    "Margem": 0
}, {
    "ID": "I22",
    "Valor": 0,
    "Quantidade": 0,
    "Margem": 0
}, {
    "ID": "I23",
    "Valor": 0,
    "Quantidade": 0,
    "Margem": 0
}, {
    "ID": "I24",
    "Valor": 0,
    "Quantidade": 0,
    "Margem": 0
}, {
    "ID": "I25",
    "Valor": 0,
    "Quantidade": 0,
    "Margem": 0
}, {
    "ID": "I26",
    "Valor": 0,
    "Quantidade": 0,
    "Margem": 0
}, {
    "ID": "I27",
    "Valor": 0,
    "Quantidade": 0,
    "Margem": 0
}, {
    "ID": "I28",
    "Valor": 0,
    "Quantidade": 0,
    "Margem": 0
}, {
    "ID": "I29",
    "Valor": 0,
    "Quantidade": 0,
    "Margem": 0
}, {
    "ID": "I30",
    "Valor": 0,
    "Quantidade": 0,
    "Margem": 0
}, {
    "ID": "I31",
    "Valor": 0,
    "Quantidade": 0,
    "Margem": 0
}, {
    "ID": "I32",
    "Valor": 0,
    "Quantidade": 0,
    "Margem": 0
}, {
    "ID": "I33",
    "Valor": 0,
    "Quantidade": 0,
    "Margem": 0
}, {
    "ID": "I34",
    "Valor": 0,
    "Quantidade": 0,
    "Margem": 0
}, {
    "ID": "I35",
    "Valor": 0,
    "Quantidade": 0,
    "Margem": 0
}, {
    "ID": "I36",
    "Valor": 0,
    "Quantidade": 0,
    "Margem": 0
}, {
    "ID": "I37",
    "Valor": 0,
    "Quantidade": 0,
    "Margem": 0
}, {
    "ID": "I38",
    "Valor": 0,
    "Quantidade": 0,
    "Margem": 0
}, {
    "ID": "I39",
    "Valor": 0,
    "Quantidade": 0,
    "Margem": 0
}, {
    "ID": "I40",
    "Valor": 0,
    "Quantidade": 0,
    "Margem": 0
}, {
    "ID": "I41",
    "Valor": 0,
    "Quantidade": 0,
    "Margem": 0
}, {
    "ID": "I42",
    "Valor": 0,
    "Quantidade": 0,
    "Margem": 0
}, {
    "ID": "I43",
    "Valor": 0,
    "Quantidade": 0,
    "Margem": 0
}, {
    "ID": "I44",
    "Valor": 0,
    "Quantidade": 0,
    "Margem": 0
}, {
    "ID": "I45",
    "Valor": 0,
    "Quantidade": 0,
    "Margem": 0
}, {
    "ID": "I46",
    "Valor": 0,
    "Quantidade": 0,
    "Margem": 0
}, {
    "ID": "I47",
    "Valor": 0,
    "Quantidade": 0,
    "Margem": 0
}, {
    "ID": "I48",
    "Valor": 0,
    "Quantidade": 0,
    "Margem": 0
}, {
    "ID": "I49",
    "Valor": 0,
    "Quantidade": 0,
    "Margem": 0
}, {
    "ID": "I50",
    "Valor": 0,
    "Quantidade": 0,
    "Margem": 0
}, {
    "ID": "I51",
    "Valor": 0,
    "Quantidade": 0,
    "Margem": 0
}, {
    "ID": "I52",
    "Valor": 0,
    "Quantidade": 0,
    "Margem": 0
}, {
    "ID": "I53",
    "Valor": 0,
    "Quantidade": 0,
    "Margem": 0
}, {
    "ID": "I54",
    "Valor": 0,
    "Quantidade": 0,
    "Margem": 0
}, {
    "ID": "I55",
    "Valor": 0,
    "Quantidade": 0,
    "Margem": 0
}, {
    "ID": "I56",
    "Valor": 0,
    "Quantidade": 0,
    "Margem": 0
}, {
    "ID": "I57",
    "Valor": 0,
    "Quantidade": 0,
    "Margem": 0
}, {
    "ID": "I58",
    "Valor": 0,
    "Quantidade": 0,
    "Margem": 0
}, {
    "ID": "I59",
    "Valor": 0,
    "Quantidade": 0,
    "Margem": 0
}, {
    "ID": "I60",
    "Valor": 0,
    "Quantidade": 0,
    "Margem": 0
}]
